LICENSE
README.md
setup.py
somerandomapi/__init__.py
somerandomapi/endpoint.py
somerandomapi/http.py
somerandomapi/sync_async_handler.py
somerandomapi/structures/animal.py
somerandomapi/structures/anime.py
somerandomapi/structures/fact.py
somerandomapi/structures/filters.py
somerandomapi/structures/image.py
somerandomapi/structures/others.py
somerandomapi/structures/welcome.py
somerandomapiml.egg-info/PKG-INFO
somerandomapiml.egg-info/SOURCES.txt
somerandomapiml.egg-info/dependency_links.txt
somerandomapiml.egg-info/requires.txt
somerandomapiml.egg-info/top_level.txt