Metadata-Version: 2.1
Name: somerandomapiml
Version: 1.0.2
Summary: Easy to use API Wrapper for somerandomapi.ml. 
Home-page: https://github.com/m-y-x-i/some-random-api-API-Wrapper
Author: Myxi
Author-email: myxi@duck.com
License: GNU GPLv3
Platform: UNKNOWN
Requires-Python: >=3.6
License-File: LICENSE
